cryptobots/__init__.py
cryptobots/_cli/__init__.py
cryptobots/_cli/cli.py
cryptobots/_cli/constants.py
cryptobots/_cli/utilities.py
cryptobots/config/__init__.py
cryptobots/config/breakout.yaml
cryptobots/config/cc.yaml
cryptobots/config/emac.yaml
cryptobots/config/grid.yaml
cryptobots/config/range.yaml
cryptobots/config/twap.yaml
cryptobots/strategies/__init__.py
cryptobots/strategies/breakout.py
cryptobots/strategies/cc.py
cryptobots/strategies/emac.py
cryptobots/strategies/grid.py
cryptobots/strategies/range.py
cryptobots/strategies/twap.py
cryptobots-0.5.3.dist-info/LICENSE
cryptobots-0.5.3.dist-info/METADATA
cryptobots-0.5.3.dist-info/WHEEL
cryptobots-0.5.3.dist-info/entry_points.txt
cryptobots-0.5.3.dist-info/top_level.txt
cryptobots-0.5.3.dist-info/RECORD
