Metadata-Version: 2.1
Name: cryptobots
Version: 0.5.3
Summary: Cyptocurrency trading bots
Project-URL: Repository, https://github.com/kieran-mackle/cryptobots
Project-URL: Issues, https://github.com/kieran-mackle/cryptobots/issues
Project-URL: Changelog, https://github.com/kieran-mackle/cryptobots/blob/main/CHANGELOG.md
Classifier: Programming Language :: Python :: 3
Classifier: License :: OSI Approved :: MIT License
Classifier: Operating System :: OS Independent
Requires-Python: >=3.11
License-File: LICENSE
Requires-Dist: autotrader >=1.1.2
Requires-Dist: ccxt
Requires-Dist: Click
Requires-Dist: trogon
Requires-Dist: johnnydep
Provides-Extra: dev
Requires-Dist: black >=23.9.1 ; extra == 'dev'
Requires-Dist: commitizen >=3.10.0 ; extra == 'dev'
Requires-Dist: pre-commit >=3.4.0 ; extra == 'dev'
